celeste_speech_generation/__init__.py
celeste_speech_generation/client.py
celeste_speech_generation/constraints.py
celeste_speech_generation/io.py
celeste_speech_generation/languages.py
celeste_speech_generation/models.py
celeste_speech_generation/parameters.py
celeste_speech_generation/py.typed
celeste_speech_generation/streaming.py
celeste_speech_generation/voices.py
celeste_speech_generation/providers/__init__.py
celeste_speech_generation/providers/elevenlabs/__init__.py
celeste_speech_generation/providers/elevenlabs/client.py
celeste_speech_generation/providers/elevenlabs/models.py
celeste_speech_generation/providers/elevenlabs/parameters.py
celeste_speech_generation/providers/elevenlabs/streaming.py
celeste_speech_generation/providers/elevenlabs/voices.py
celeste_speech_generation/providers/google/__init__.py
celeste_speech_generation/providers/google/client.py
celeste_speech_generation/providers/google/mappings.py
celeste_speech_generation/providers/google/models.py
celeste_speech_generation/providers/google/parameters.py
celeste_speech_generation/providers/google/voices.py
celeste_speech_generation/providers/gradium/__init__.py
celeste_speech_generation/providers/gradium/client.py
celeste_speech_generation/providers/gradium/models.py
celeste_speech_generation/providers/gradium/parameters.py
celeste_speech_generation/providers/gradium/voices.py
celeste_speech_generation/providers/openai/__init__.py
celeste_speech_generation/providers/openai/client.py
celeste_speech_generation/providers/openai/models.py
celeste_speech_generation/providers/openai/parameters.py
celeste_speech_generation/providers/openai/voices.py
celeste_speech_generation-0.3.7.dist-info/METADATA
celeste_speech_generation-0.3.7.dist-info/WHEEL
celeste_speech_generation-0.3.7.dist-info/entry_points.txt
celeste_speech_generation-0.3.7.dist-info/RECORD
